hamana/__init__.py
hamana/connector/__init__.py
hamana/connector/db/__init__.py
hamana/connector/db/base.py
hamana/connector/db/exceptions.py
hamana/connector/db/hamana.py
hamana/connector/db/interface.py
hamana/connector/db/oracle.py
hamana/connector/db/query.py
hamana/connector/db/schema.py
hamana/connector/db/sqlite.py
hamana/connector/db/teradata.py
hamana/connector/file/__init__.py
hamana/connector/file/csv.py
hamana/connector/file/exceptions.py
hamana/connector/file/warnings.py
hamana/core/__init__.py
hamana/core/column.py
hamana/core/exceptions.py
hamana/core/identifier.py
hamana/core/warnings.py
hamana-1.0.1.dist-info/METADATA
hamana-1.0.1.dist-info/WHEEL
hamana-1.0.1.dist-info/licenses/LICENSE
hamana-1.0.1.dist-info/RECORD
