Metadata-Version: 2.3
Name: hamana
Version: 1.0.1
Summary: A python library for seamless data extraction, storage, and SQL-based analysis using pandas and SQLite.
Project-URL: Homepage, https://github.com/zazza123/hamana
Project-URL: Repository, https://github.com/zazza123/hamana
Project-URL: Documentation, https://zazza123.github.io/hamana
Author: Andrea Zanini
Classifier: Development Status :: 1 - Planning
Classifier: Environment :: Web Environment
Classifier: Intended Audience :: Developers
Classifier: Intended Audience :: Information Technology
Classifier: License :: OSI Approved :: BSD License
Classifier: Operating System :: OS Independent
Classifier: Programming Language :: Python
Classifier: Programming Language :: Python :: 3
Classifier: Programming Language :: Python :: 3.12
Classifier: Topic :: Database
Classifier: Topic :: Scientific/Engineering :: Information Analysis
Requires-Python: >=3.12
Requires-Dist: oracledb>=2.4.1
Requires-Dist: pandas>=2.2.3
Requires-Dist: teradatasql>=20.0.0.31
